mdc_dlp/__init__.py
mdc_dlp/client.py
mdc_dlp/dataset.py
mdc_dlp-0.0.1a0.dist-info/licenses/LICENSE
mdc_dlp-0.0.1a0.dist-info/WHEEL
mdc_dlp-0.0.1a0.dist-info/entry_points.txt
mdc_dlp-0.0.1a0.dist-info/METADATA
mdc_dlp-0.0.1a0.dist-info/RECORD
