Metadata-Version: 2.4
Name: mdc-dlp
Version: 0.0.1a0
Summary: A Python package for interfacing with the Mozilla Data Collective's API
Author: Sarthak Bisht
Author-email: Sarthak Bisht <sbisht@cs.cmu.edu>
License-Expression: MPL-2.0
License-File: LICENSE
Classifier: Programming Language :: Python :: 3
Classifier: Operating System :: OS Independent
Requires-Dist: pandas>=2.0.0
Requires-Dist: python-dotenv>=1.0.0
Requires-Dist: requests>=2.0.0
Requires-Dist: pytest>=7.0.0 ; extra == 'dev'
Requires-Dist: pytest-cov>=4.0.0 ; extra == 'dev'
Requires-Dist: black>=23.0.0 ; extra == 'dev'
Requires-Dist: ruff>=0.1.0 ; extra == 'dev'
Requires-Dist: mypy>=1.0.0 ; extra == 'dev'
Requires-Dist: pre-commit>=3.0.0 ; extra == 'dev'
Requires-Dist: bump2version>=1.0.0 ; extra == 'dev'
Requires-Python: >=3.9
Project-URL: Homepage, https://github.com/BishtSarthak/mdc-dlp/
Project-URL: Issues, https://github.com/BishtSarthak/mdc-dlp/issues
Provides-Extra: dev
